polyhedral_gravity.cp39-win_amd64.pyd
polyhedral_gravity-3.3.1.dist-info/licenses/LICENSE
polyhedral_gravity-3.3.1.dist-info/METADATA
polyhedral_gravity-3.3.1.dist-info/WHEEL
polyhedral_gravity-3.3.1.dist-info/top_level.txt
polyhedral_gravity-3.3.1.dist-info/RECORD
