Metadata-Version: 2.4
Name: polyhedral_gravity
Version: 3.3.1
Summary: Package to compute full gravity tensor of a given constant density polyhedron for arbitrary points according to the geodetic convention
Author: Jonas Schuhmacher
Author-email: jonas.schuhmacher@tum.de
License: GPLv3
Project-URL: Homepage, https://github.com/esa/polyhedral-gravity-model
Project-URL: Source, https://github.com/esa/polyhedral-gravity-model
Project-URL: Documentation, https://esa.github.io/polyhedral-gravity-model/
Project-URL: Issues, https://github.com/esa/polyhedral-gravity-model/issues
Project-URL: Changelog, https://github.com/esa/polyhedral-gravity-model/releases
Classifier: Development Status :: 5 - Production/Stable
Classifier: License :: OSI Approved :: GNU General Public License v3 (GPLv3)
Classifier: Programming Language :: C++
Classifier: Programming Language :: Python
Classifier: Operating System :: Microsoft :: Windows
Classifier: Operating System :: MacOS
Classifier: Operating System :: POSIX :: Linux
Classifier: Intended Audience :: Science/Research
Classifier: Topic :: Scientific/Engineering :: Physics
Requires-Python: >=3.9
License-File: LICENSE
Dynamic: author
Dynamic: author-email
Dynamic: classifier
Dynamic: description
Dynamic: description-content-type
Dynamic: license
Dynamic: license-file
Dynamic: project-url
Dynamic: requires-python
Dynamic: summary
